pps/__init__.py
pps/ppscore.py
pps_python-0.0.8.dist-info/LICENSE
pps_python-0.0.8.dist-info/METADATA
pps_python-0.0.8.dist-info/WHEEL
pps_python-0.0.8.dist-info/top_level.txt
pps_python-0.0.8.dist-info/RECORD
