Metadata-Version: 2.1
Name: pps-python
Version: 0.0.8
Summary: Customised Python Functions for calculating Predictive Power Score
Home-page: https://github.com/akhil14shukla/ppscore
Author: Akhil Shukla (akhil14shukla)
License: GNU v3.0
Classifier: Programming Language :: Python :: 3.7
Classifier: License :: OSI Approved :: GNU General Public License v3 (GPLv3)
License-File: LICENSE
Requires-Dist: pandas (<2.0.0,>=1.0.0)
Requires-Dist: scikit-learn (<1.0.0,>=0.20.2)
Requires-Dist: numpy
